{
	"cli": {
		"version": ">= 16.12.0",
		"appVersionSource": "remote"
	},
	"build": {
		"development": {
			"developmentClient": true,
			"distribution": "internal",
			"env": {
				"EXPO_PUBLIC_API_URL": "https://brie-staging-api.onrender.com",
				"EXPO_PUBLIC_ENV": "dev"
			}
		},
		"preview": {
			"channel": "preview",
			"distribution": "internal",
			"autoIncrement": true,
			"env": {
				"EXPO_PUBLIC_API_URL": "https://brie-staging-api.onrender.com",
				"EXPO_PUBLIC_ENV": "staging"
			}
		},
		"testflight": {
			"channel": "testflight",
			"distribution": "store",
			"autoIncrement": true,
			"env": {
				"EXPO_PUBLIC_API_URL": "https://brie-staging-api.onrender.com",
				"EXPO_PUBLIC_ENV": "testflight"
			},
			"ios": {
				"image": "latest"
			}
		},
		"production": {
			"channel": "production",
			"distribution": "store",
			"autoIncrement": true,
			"env": {
				"EXPO_PUBLIC_API_URL": "https://brie-staging-api.onrender.com",
				"EXPO_PUBLIC_ENV": "production"
			}
		}
	},
	"submit": {
		"testflight": {
			"ios": {
				"ascAppId": "YOUR_APP_ID_FROM_ASC"
			}
		},
		"production": {
			"ios": {
				"ascAppId": "YOUR_APP_ID_FROM_ASC"
			}
		}
	}
}
